klvm_tools_rs-0.4.0.dist-info/METADATA
klvm_tools_rs-0.4.0.dist-info/WHEEL
klvm_tools_rs-0.4.0.dist-info/license_files/LICENSE
klvm_tools_rs/__init__.py
klvm_tools_rs/klvm_tools_rs.abi3.so
klvm_tools_rs-0.4.0.dist-info/RECORD
