Metadata-Version: 2.3
Name: klvm_tools_rs
Version: 0.4.0
License-File: LICENSE
Summary: tools for working with chiklisp language; compiler, repl, python and wasm bindings
Keywords: chik,chiklisp,klvm
Author: Art Yerkes <art.yerkes@gmail.com>
Author-email: Art Yerkes <art.yerkes@gmail.com>
License: Apache-2.0
Project-URL: Source Code, https://github.com/Chik-Network/klvm_tools_rs
